pulseblaster/PBInd.py
pulseblaster/__init__.py
pulseblaster/spinapi.py
pulseblaster-1.0.1.dist-info/LICENSE
pulseblaster-1.0.1.dist-info/METADATA
pulseblaster-1.0.1.dist-info/WHEEL
pulseblaster-1.0.1.dist-info/top_level.txt
pulseblaster-1.0.1.dist-info/RECORD
