Metadata-Version: 2.1
Name: pulseblaster
Version: 1.0.1
Summary: Python control code for Pulseblaster pulse generation hardware.
Author-email: Zeeshawn Kazi <zeeshawn@uw.edu>, "G. Adam Cox" <gadamc@gmail.com>
Maintainer-email: "G. Adam Cox" <gadamc@gmail.com>, Maxwell Parsons <mfpars@uw.edu>
License: Creative Commons Legal Code
Project-URL: Homepage, https://github.com/qt3uw/pulseblaster
Project-URL: Source, https://github.com/qt3uw/pulseblaster
Project-URL: Bug Tracker, https://github.com/qt3uw/pulseblaster/issues
Project-URL: Changelog, https://github.com/qt3uw/pulseblaster/releases
Keywords: qt3,pulseblaster,ttl,pulse generator
Classifier: Development Status :: 5 - Production/Stable
Classifier: Intended Audience :: Science/Research
Classifier: Topic :: Scientific/Engineering :: Physics
Classifier: Topic :: Scientific/Engineering
Classifier: License :: OSI Approved :: BSD License
Classifier: Programming Language :: Python :: 3.8
Classifier: Programming Language :: Python :: 3.9
Classifier: Programming Language :: Python :: 3.10
Classifier: Programming Language :: Python :: 3.11
Classifier: Programming Language :: Python :: 3 :: Only
Requires-Python: >=3.8
License-File: LICENSE
Requires-Dist: numpy
